
[
{"date":"2026-03-28", "time": "20:00", venue":"Foresters","city":"Andover"},
{"date":"2026-04-03","venue":"Monmouth Ash","city":"Verwood"},
{"date":"2026-04-18","venue":"The Southwestern Arms","city":"St Denys, Southampton"},
{"date":"2026-05-02","venue":"Netheravon MWC","city":"Netheravon"},
{"date":"2026-05-09","venue":"Qudos","city":"Salisbury"},
{"date":"2026-05-30","venue":"Rose & Crown","city":"Bulford"},
{"date":"2026-06-20","venue":"The Angel Inn","city":"Andover"},
{"date":"2026-06.26","venue":"The Dolphin","city":"St Denys, Southampton"},
{"date":"2026-07-11","venue":"Romsey Beggars Fair","city":"Romsey"},
{"date":"2026-08-01","venue":"Foresters","city":"Andover"},
{"date":"2026-08-29","venue":"Burbage Royal British Legion","city":"Burbage"},
{"date":"2026-10-10","venue":"The Southwestern Arms","city":"Southampton"},
{"date":"2026-11-14","venue":"The Plough Inn","city":"Durrington"},
{"date":"2026-12-12","venue":"The Southwestern Arms","city":"St Denys, Southampton"}
]
